tg_runner_cli/__init__.py
tg_runner_cli/cli.py
tg_runner_cli-1.0.0.dist-info/licenses/LICENSE
tg_runner_cli-1.0.0.dist-info/METADATA
tg_runner_cli-1.0.0.dist-info/WHEEL
tg_runner_cli-1.0.0.dist-info/entry_points.txt
tg_runner_cli-1.0.0.dist-info/top_level.txt
tg_runner_cli-1.0.0.dist-info/RECORD
