Metadata-Version: 2.4
Name: tg-runner-cli
Version: 1.0.0
Summary: CLI for managing Telegram bots via TG Runner
Author-email: TimaxLacs <timaxlacs@github.com>
License: MIT
Project-URL: Homepage, https://github.com/TimaxLacs/tg-runner-cli
Project-URL: Repository, https://github.com/TimaxLacs/tg-runner-cli
Project-URL: Issues, https://github.com/TimaxLacs/tg-runner-cli/issues
Keywords: telegram,bot,cli,docker,runner
Classifier: Development Status :: 4 - Beta
Classifier: Intended Audience :: Developers
Classifier: License :: OSI Approved :: MIT License
Classifier: Programming Language :: Python :: 3
Classifier: Programming Language :: Python :: 3.10
Classifier: Programming Language :: Python :: 3.11
Classifier: Programming Language :: Python :: 3.12
Classifier: Environment :: Console
Classifier: Topic :: Communications :: Chat
Requires-Python: >=3.10
License-File: LICENSE
Requires-Dist: requests>=2.28.0
Requires-Dist: rich>=13.0.0
Dynamic: license-file
